{"minecraft:recipes/decorations/crafting_table":{"criteria":{"unlock_right_away":"2026-03-08 07:02:48 +0000"},"done":true},"minecraft:recipes/transportation/cherry_boat":{"criteria":{"in_water":"2026-03-08 07:12:05 +0000"},"done":true},"minecraft:recipes/transportation/bamboo_raft":{"criteria":{"in_water":"2026-03-08 07:12:05 +0000"},"done":true},"minecraft:recipes/transportation/spruce_boat":{"criteria":{"in_water":"2026-03-08 07:12:05 +0000"},"done":true},"minecraft:recipes/transportation/birch_boat":{"criteria":{"in_water":"2026-03-08 07:12:05 +0000"},"done":true},"minecraft:recipes/transportation/oak_boat":{"criteria":{"in_water":"2026-03-08 07:12:05 +0000"},"done":true},"minecraft:recipes/transportation/mangrove_boat":{"criteria":{"in_water":"2026-03-08 07:12:05 +0000"},"done":true},"minecraft:recipes/decorations/torch":{"criteria":{"has_stone_pickaxe":"2026-03-08 07:02:49 +0000"},"done":true},"minecraft:story/upgrade_tools":{"criteria":{"stone_pickaxe":"2026-03-08 07:02:49 +0000"},"done":true},"minecraft:recipes/transportation/acacia_boat":{"criteria":{"in_water":"2026-03-08 07:12:05 +0000"},"done":true},"minecraft:recipes/transportation/pale_oak_boat":{"criteria":{"in_water":"2026-03-08 07:12:05 +0000"},"done":true},"minecraft:adventure/adventuring_time":{"criteria":{"minecraft:deep_cold_ocean":"2026-03-08 07:19:00 +0000","minecraft:forest":"2026-03-08 07:03:53 +0000","minecraft:mangrove_swamp":"2026-03-08 07:13:43 +0000","minecraft:sparse_jungle":"2026-03-08 07:16:31 +0000","minecraft:jungle":"2026-03-08 07:13:05 +0000","minecraft:deep_ocean":"2026-03-08 07:19:52 +0000","minecraft:swamp":"2026-03-08 07:02:49 +0000","minecraft:dripstone_caves":"2026-03-08 07:09:47 +0000","minecraft:savanna":"2026-03-08 07:07:29 +0000"},"done":false},"minecraft:recipes/transportation/jungle_boat":{"criteria":{"in_water":"2026-03-08 07:12:05 +0000"},"done":true},"minecraft:recipes/transportation/dark_oak_boat":{"criteria":{"in_water":"2026-03-08 07:12:05 +0000"},"done":true},"DataVersion":4671}